ctinker/LICENSE
ctinker/__init__.py
ctinker/_supervisor.py
ctinker-0.0.4.data/scripts/ctinker
ctinker-0.0.4.dist-info/METADATA
ctinker-0.0.4.dist-info/WHEEL
ctinker-0.0.4.dist-info/namespace_packages.txt
ctinker-0.0.4.dist-info/top_level.txt
ctinker-0.0.4.dist-info/zip-safe
ctinker-0.0.4.dist-info/RECORD
