Metadata-Version: 2.1
Name: ctinker
Version: 0.0.4
Summary: CTinker is a C project introspection and augmentation tool
Home-page: https://github.com/karellen/ctinker
Author: Karellen, Inc.
Author-email: supervisor@karellen.co
Maintainer: Arcadiy Ivanov
Maintainer-email: arcadiy@karellen.co
License: Apache License, Version 2.0
Project-URL: Bug Tracker, https://github.com/karellen/ctinker/issues
Project-URL: Documentation, https://github.com/karellen/ctinker/
Project-URL: Source Code, https://github.com/karellen/ctinker/
Keywords: C C++ build make ninja llvm clang flags intercept augment
Platform: UNKNOWN
Classifier: License :: OSI Approved :: Apache Software License
Classifier: Programming Language :: Python :: 3.6
Classifier: Programming Language :: Python :: 3.7
Classifier: Programming Language :: Python :: 3.8
Classifier: Operating System :: MacOS :: MacOS X
Classifier: Operating System :: POSIX
Classifier: Operating System :: POSIX :: Linux
Classifier: Programming Language :: C
Classifier: Programming Language :: C++
Classifier: Topic :: Software Development :: Build Tools
Classifier: Topic :: Software Development :: Compilers
Classifier: Topic :: Software Development :: Assemblers
Classifier: Topic :: Software Development :: Pre-processors
Classifier: Topic :: Utilities
Classifier: Intended Audience :: Developers
Classifier: Development Status :: 4 - Beta
Requires-Python: >=3.6
